README.md
wigle2kml.py
wigle2kml_py-0.1.2.dist-info/METADATA
wigle2kml_py-0.1.2.dist-info/WHEEL
wigle2kml_py-0.1.2.dist-info/entry_points.txt
wigle2kml_py-0.1.2.dist-info/RECORD
