Metadata-Version: 2.4
Name: wigle2kml-py
Version: 0.1.2
Summary: Convert Wigle API JSON output to KML for Google Earth and other geo tools.
Project-URL: Homepage, https://github.com/DefensiveOrigins/Wigle2KML-py
Project-URL: Source, https://github.com/DefensiveOrigins/Wigle2KML-py
Project-URL: Issues, https://github.com/DefensiveOrigins/Wigle2KML-py/issues
Author: Kent Ickler
License: MIT
Keywords: geospatial,google-earth,kml,wifi,wigle
Classifier: Development Status :: 3 - Alpha
Classifier: Intended Audience :: Information Technology
Classifier: Intended Audience :: System Administrators
Classifier: Programming Language :: Python
Classifier: Programming Language :: Python :: 3
Classifier: Programming Language :: Python :: 3 :: Only
Classifier: Programming Language :: Python :: 3.8
Classifier: Programming Language :: Python :: 3.9
Classifier: Programming Language :: Python :: 3.10
Classifier: Programming Language :: Python :: 3.11
Classifier: Topic :: Security
Classifier: Topic :: Utilities
Requires-Python: >=3.8
